neko_hacker/__init__.py
neko_hacker/neko_hacker.py
neko_hacker-0.0.1.dist-info/LICENSE
neko_hacker-0.0.1.dist-info/METADATA
neko_hacker-0.0.1.dist-info/WHEEL
neko_hacker-0.0.1.dist-info/top_level.txt
neko_hacker-0.0.1.dist-info/RECORD
