Metadata-Version: 2.1
Name: neko-hacker
Version: 0.0.1
Summary: neko-hacker is a library for Neko Hacker and their fans.
Home-page: https://github.com/chanyou0311/neko-hacker
Author: chanyou0311
Author-email: chanyou0311@gmail.com
License: MIT License
Platform: UNKNOWN
Classifier: License :: OSI Approved :: MIT License
Classifier: Programming Language :: Python :: 3
Classifier: Operating System :: OS Independent
